fabric_ceph/__init__.py
fabric_ceph/__main__.py
fabric_ceph/config.yml
fabric_ceph/openapi.yml
fabric_ceph/swagger_code_gen.sh
fabric_ceph/common/__init__.py
fabric_ceph/common/config.py
fabric_ceph/common/globals.py
fabric_ceph/common/graceful_interrupt_handler.py
fabric_ceph/external_api/__init__.py
fabric_ceph/external_api/core_api.py
fabric_ceph/openapi_server/__init__.py
fabric_ceph/openapi_server/__main__.py
fabric_ceph/openapi_server/encoder.py
fabric_ceph/openapi_server/typing_utils.py
fabric_ceph/openapi_server/util.py
fabric_ceph/openapi_server/controllers/__init__.py
fabric_ceph/openapi_server/controllers/ceph_fs_controller.py
fabric_ceph/openapi_server/controllers/cluster_user_controller.py
fabric_ceph/openapi_server/controllers/security_controller.py
fabric_ceph/openapi_server/controllers/version_controller.py
fabric_ceph/openapi_server/models/__init__.py
fabric_ceph/openapi_server/models/base_model.py
fabric_ceph/openapi_server/models/capability.py
fabric_ceph/openapi_server/models/ceph_user.py
fabric_ceph/openapi_server/models/create_or_update_user_request.py
fabric_ceph/openapi_server/models/export_users_request.py
fabric_ceph/openapi_server/models/status200_ok_no_content.py
fabric_ceph/openapi_server/models/status200_ok_no_content_data.py
fabric_ceph/openapi_server/models/status200_ok_paginated.py
fabric_ceph/openapi_server/models/status200_ok_single.py
fabric_ceph/openapi_server/models/status400_bad_request.py
fabric_ceph/openapi_server/models/status400_bad_request_errors.py
fabric_ceph/openapi_server/models/status401_unauthorized.py
fabric_ceph/openapi_server/models/status401_unauthorized_errors.py
fabric_ceph/openapi_server/models/status403_forbidden.py
fabric_ceph/openapi_server/models/status403_forbidden_errors.py
fabric_ceph/openapi_server/models/status404_not_found.py
fabric_ceph/openapi_server/models/status404_not_found_errors.py
fabric_ceph/openapi_server/models/status500_internal_server_error.py
fabric_ceph-1.0.0.dist-info/licenses/LICENSE
fabric_ceph-1.0.0.dist-info/WHEEL
fabric_ceph-1.0.0.dist-info/METADATA
fabric_ceph-1.0.0.dist-info/RECORD
