Metadata-Version: 2.4
Name: fabric_ceph
Version: 1.0.0
Summary: Fabric Ceph Service
Keywords: Swagger,Fabric  Ceph Service
Author-email: Komal Thareja <kthare10@renci.org>
Requires-Python: >=3.9
Classifier: Programming Language :: Python :: 3
Classifier: License :: OSI Approved :: MIT License
Classifier: Operating System :: OS Independent
License-File: LICENSE
Requires-Dist: requests >= 2.28.1
Requires-Dist: waitress
Requires-Dist: connexion==2.14.2
Requires-Dist: swagger-ui-bundle>= 0.0.2
Requires-Dist: PyYAML
Requires-Dist: fabric_fss_utils==1.6.0
Requires-Dist: fabric_fss_utils>=1.6.0
Requires-Dist: fabric_credmgr_client>=1.6.2
Requires-Dist: paramiko
Requires-Dist: pytest ; extra == "test"
Requires-Dist: flask_testing ; extra == "test"
Requires-Dist: coverage>=4.0.3 ; extra == "test"
Requires-Dist: nose>=1.3.7 ; extra == "test"
Requires-Dist: pluggy>=0.3.1 ; extra == "test"
Requires-Dist: py>=1.4.31 ; extra == "test"
Requires-Dist: randomize>=0.13 ; extra == "test"
Project-URL: Home, https://fabric-testbed.net/
Project-URL: Sources, https://github.com/fabric-testbed/fabric_ceph
Provides-Extra: test
